sstc_core/__init__.py
sstc_core/sites/__init__.py
sstc_core/sites/spectral/__init__.py
sstc_core/sites/spectral/assets/SITES_logo_small.jpeg
sstc_core/sites/spectral/assets/SITES_spectral_LOGO.png
sstc_core/sites/spectral/catalog.py
sstc_core/sites/spectral/config/__init__.py
sstc_core/sites/spectral/config/catalog_db_filepaths.yaml
sstc_core/sites/spectral/config/catalog_default_filepaths.yaml
sstc_core/sites/spectral/config/db_schemas/__init__.py
sstc_core/sites/spectral/config/db_schemas/platforms_schemas.py
sstc_core/sites/spectral/config/ecosystems.yaml
sstc_core/sites/spectral/config/github_stations_catalog_db_backups.yaml
sstc_core/sites/spectral/config/locations/__init__.py
sstc_core/sites/spectral/config/locations/locations_abisko.yaml
sstc_core/sites/spectral/config/locations/locations_asa.yaml
sstc_core/sites/spectral/config/locations/locations_grimso.yaml
sstc_core/sites/spectral/config/locations/locations_lonnstorp.yaml
sstc_core/sites/spectral/config/locations/locations_robacksdalen.yaml
sstc_core/sites/spectral/config/locations/locations_skogaryd.yaml
sstc_core/sites/spectral/config/locations/locations_svartverget.yaml
sstc_core/sites/spectral/config/maintainance_status.yaml
sstc_core/sites/spectral/config/phenocam_flags.yaml
sstc_core/sites/spectral/config/phenocam_products.yaml
sstc_core/sites/spectral/config/platforms/__init__.py
sstc_core/sites/spectral/config/platforms/platforms_abisko.yaml
sstc_core/sites/spectral/config/platforms/platforms_asa.yaml
sstc_core/sites/spectral/config/platforms/platforms_grimso.yaml
sstc_core/sites/spectral/config/platforms/platforms_lonnstorp.yaml
sstc_core/sites/spectral/config/platforms/platforms_robacksdalen.yaml
sstc_core/sites/spectral/config/platforms/platforms_skogaryd.yaml
sstc_core/sites/spectral/config/platforms/platforms_svartberget.yaml
sstc_core/sites/spectral/config/stations_names.yaml
sstc_core/sites/spectral/data_products/__init__.py
sstc_core/sites/spectral/data_products/phenocams.py
sstc_core-0.21.2.dist-info/METADATA
sstc_core-0.21.2.dist-info/WHEEL
sstc_core-0.21.2.dist-info/RECORD
