Metadata-Version: 2.1
Name: sstc-core
Version: 0.21.2
Summary: 
Home-page: https://pypi.org/project/sstc-core/
Author: Jobelund
Author-email: 124563223+jobelund@users.noreply.github.com
Requires-Python: >=3.11,<4.0
Classifier: Programming Language :: Python :: 3
Classifier: Programming Language :: Python :: 3.11
Classifier: Programming Language :: Python :: 3.12
Requires-Dist: duckdb (>=1.0,<2.0)
Requires-Dist: importlib-metadata (>=8.5.0,<9.0.0)
Requires-Dist: keyring (>=25.2.1,<26.0.0)
Requires-Dist: mkdocs (>=1.5.3,<2.0.0)
Requires-Dist: mkdocs_material (>=9.5.30,<10.0.0)
Requires-Dist: opencv-python (>=4.10.0.84,<5.0.0.0)
Requires-Dist: paramiko (>=3.4,<4.0)
Requires-Dist: pillow (>=10.4.0,<11.0.0)
Requires-Dist: pyperclip (>=1.9.0,<2.0.0)
Requires-Dist: pysolar (>=0.11,<0.12)
Requires-Dist: pyyaml (>=6.0.1,<7.0.0)
Requires-Dist: reportlab (>=4.2.4,<5.0.0)
